opinionated_mixins/__about__.py
opinionated_mixins/__init__.py
opinionated_mixins/contrib/dataclasses/__init__.py
opinionated_mixins/contrib/mongoengine/__init__.py
opinionated_mixins/contrib/odmantic/__init__.py
opinionated_mixins/contrib/pydantic/__init__.py
opinionated_mixins/contrib/sqlalchemy/__init__.py
opinionated_mixins/contrib/sqlmodel/__init__.py
opinionated_mixins/contrib/wtforms/__init__.py
opinionated_mixins-0.0.1.dist-info/METADATA
opinionated_mixins-0.0.1.dist-info/WHEEL
opinionated_mixins-0.0.1.dist-info/licenses/LICENSE
opinionated_mixins-0.0.1.dist-info/RECORD
