Metadata-Version: 2.1
Name: opinionated-mixins
Version: 0.0.1
Summary: Opinionated set of mixins. Implemented in Pydantic, SQLAlchemy, MongoEngine, ODMantic, etc.
Project-URL: Documentation, https://github.com/hasansezertasan/opinionated-mixins#readme
Project-URL: Issues, https://github.com/hasansezertasan/opinionated-mixins/issues
Project-URL: Source, https://github.com/hasansezertasan/opinionated-mixins
Author-email: Hasan Sezer Taşan <hasansezertasan@gmail.com>
License-Expression: MIT
License-File: LICENSE
Classifier: Development Status :: 4 - Beta
Classifier: Programming Language :: Python
Classifier: Programming Language :: Python :: 3.8
Classifier: Programming Language :: Python :: 3.9
Classifier: Programming Language :: Python :: 3.10
Classifier: Programming Language :: Python :: 3.11
Classifier: Programming Language :: Python :: 3.12
Classifier: Programming Language :: Python :: Implementation :: CPython
Classifier: Programming Language :: Python :: Implementation :: PyPy
Requires-Python: >=3.8
